aw_cli-2.1.3.dist-info/licenses/LICENSE
awcli/__init__.py
awcli/anilist.py
awcli/anime.py
awcli/arg_parser.py
awcli/run.py
awcli/utilities.py
awcli/version.py
aw_cli-2.1.3.dist-info/METADATA
aw_cli-2.1.3.dist-info/WHEEL
aw_cli-2.1.3.dist-info/entry_points.txt
aw_cli-2.1.3.dist-info/top_level.txt
aw_cli-2.1.3.dist-info/RECORD
