Metadata-Version: 2.4
Name: aw-cli
Version: 2.1.3
Summary: guarda anime dal terminale e molto altro!
Home-page: https://github.com/fexh10/aw-cli
Author: fexh10
License: GPL-3.0
Requires-Python: >3.10
License-File: LICENSE
Requires-Dist: requests
Requires-Dist: pySmartDL
Requires-Dist: wheel
Requires-Dist: regex
Requires-Dist: toml
Requires-Dist: pip-system-certs
Dynamic: author
Dynamic: description
Dynamic: description-content-type
Dynamic: home-page
Dynamic: license
Dynamic: license-file
Dynamic: requires-dist
Dynamic: requires-python
Dynamic: summary
